arrow_adapters/__init__.py
arrow_adapters/auto.py
arrow_adapters/graphene.py
arrow_adapters/postgres.py
arrow_adapters/sqlalchemy.py
arrow_adapters/sqlite.py
arrow_adapters-0.0.3.dist-info/LICENSE.txt
arrow_adapters-0.0.3.dist-info/METADATA
arrow_adapters-0.0.3.dist-info/WHEEL
arrow_adapters-0.0.3.dist-info/top_level.txt
arrow_adapters-0.0.3.dist-info/RECORD
