Metadata-Version: 2.1
Name: arrow-adapters
Version: 0.0.3
Summary: arrow adapters
Home-page: https://github.com/dpep/py_arrow_adapters
Author: Daniel Pepper
License: MIT
Platform: any
Classifier: License :: OSI Approved :: MIT License
Classifier: Natural Language :: English
Classifier: Operating System :: OS Independent
Classifier: Topic :: Utilities
Requires-Dist: arrow
